[
	{
		"id": 1,
		"id_persona": 2,
		"tipo": "cumplea単os",
		"icono": "icon-birthday-cake",
		"dia": 3,
		"mes": 10,
		"anio": 0
	},
	{
		"id": 2,
		"id_persona": 2,
		"tipo": "aniversario de bodas",
		"icono": "icon-interlocking-rings",
		"dia": 9,
		"mes": 12,
		"anio": 2011
	},
	{
		"id": 3,
		"id_persona": 3,
		"tipo": "cumplea単os",
		"icono": "icon-birthday-cake",
		"dia": 15,
		"mes": 2,
		"anio": 1983
	},
	{
		"id": 4,
		"id_persona": 4,
		"tipo": "cumplea単os",
		"icono": "icon-birthday-cake",
		"dia": 25,
		"mes": 6,
		"anio": 1994
	},
	{
		"id": 5,
		"id_persona": 1,
		"tipo": "cumplea単os",
		"icono": "icon-birthday-cake",
		"dia": 9,
		"mes": 12,
		"anio": 1989
	}
]